wwsclient/__init__.py
wwsclient/__main__.py
wwsclient/client.py
wwsclient/service.py
wwsclient/util.py
wwsclient-0.0.1.2.dist-info/LICENSE
wwsclient-0.0.1.2.dist-info/METADATA
wwsclient-0.0.1.2.dist-info/WHEEL
wwsclient-0.0.1.2.dist-info/entry_points.txt
wwsclient-0.0.1.2.dist-info/top_level.txt
wwsclient-0.0.1.2.dist-info/RECORD
