Metadata-Version: 2.1
Name: wwsclient
Version: 0.0.1.2
Summary: This script will be expose all workday webservice operations
Home-page: https://github.com/hikmat30ce/Workday-Webservices-Client.git
Author: Hikmat Ullah
Author-email: me@hikmatu.com
License: MIT
Platform: UNKNOWN
Classifier: Development Status :: 1 - Planning
Classifier: Intended Audience :: Financial and Insurance Industry
Classifier: Intended Audience :: Other Audience
Classifier: Intended Audience :: Developers
Classifier: Intended Audience :: End Users/Desktop
Classifier: Programming Language :: Python :: 2
Classifier: Programming Language :: Python :: 2.7
Classifier: Programming Language :: Python :: 3
Classifier: Programming Language :: Python :: 3.4
Classifier: Programming Language :: Python :: 3.5
Classifier: Programming Language :: Python :: 3.7
Classifier: Programming Language :: Python :: 3.9
Requires-Dist: appdirs (==1.4.4)
Requires-Dist: attrs (==20.3.0)
Requires-Dist: cached-property (==1.5.2)
Requires-Dist: certifi (==2020.12.5)
Requires-Dist: chardet (==4.0.0)
Requires-Dist: defusedxml (==0.7.0)
Requires-Dist: idna (==2.10)
Requires-Dist: isodate (==0.6.0)
Requires-Dist: lxml (==4.6.3)
Requires-Dist: pytz (==2021.1)
Requires-Dist: requests (==2.25.1)
Requires-Dist: requests-file (==1.5.1)
Requires-Dist: requests-toolbelt (==0.9.1)
Requires-Dist: six (==1.15.0)
Requires-Dist: urllib3 (==1.26.5)
Requires-Dist: xmltodict (==0.12.0)
Requires-Dist: zeep (==4.0.0)
